LICENSE.txt
MANIFEST.in
README.md
setup.cfg
setup.py
stackfinder/__init__.py
stackfinder/cli.py
stackfinder/geodetics.py
stackfinder.egg-info/PKG-INFO
stackfinder.egg-info/SOURCES.txt
stackfinder.egg-info/dependency_links.txt
stackfinder.egg-info/entry_points.txt
stackfinder.egg-info/not-zip-safe
stackfinder.egg-info/pbr.json
stackfinder.egg-info/requires.txt
stackfinder.egg-info/top_level.txt